downtime_csv/__main__.py
downtime_csv-1.0.5.dist-info/LICENSE
downtime_csv-1.0.5.dist-info/METADATA
downtime_csv-1.0.5.dist-info/WHEEL
downtime_csv-1.0.5.dist-info/entry_points.txt
downtime_csv-1.0.5.dist-info/RECORD
