Metadata-Version: 2.1
Name: downtime-csv
Version: 1.0.5
Summary: A tool that measures the downtime from the user's perspective when restarting a web server and outputs it to a CSV file.
Home-page: https://github.com/procube-open/downtime-csv
Author: Mitsuru Nakakawaji
Author-email: mitsuru@procube.jp
Requires-Python: >=3.12,<4.0
Classifier: Programming Language :: Python :: 3
Classifier: Programming Language :: Python :: 3.12
Requires-Dist: aiohttp (>=3.9.5,<4.0.0)
Requires-Dist: asyncio (>=3.4.3,<4.0.0)
Project-URL: Repository, https://github.com/procube-open/downtime-csv
